{
  "display": {
    "icon": {
      "item": "player_head",
      "nbt": "{display:{Name:'{\"text\":\"Hovering Inferno\"}'},SkullOwner:'{Id:[I;259043974,944589788,-1170011413,-1573252200],Properties:{textures:[{Value:\"eyJ0ZXh0dXJlcyI6eyJTS0lOIjp7InVybCI6Imh0dHA6Ly90ZXh0dXJlcy5taW5lY3JhZnQubmV0L3RleHR1cmUvYzAyNzcwNGZmMDFiZTk0NzI5YTJkYTAyNjIyYTM4Y2ZiOWU4Yjg1ZWRkZjMyMmZmZDY4OWFlODA1ZWUxMWM3ZCJ9fX0=\"}]}}'}"
    },
    "title": {
      "translate":"incendium.advancement.infernal_dunes.inferno.summon.title","fallback":"Risen from Fire"
    },
    "description": {
      "translate":"incendium.advancement.infernal_dunes.inferno.summon.desc","fallback":"Sacrifice a nether star at an altar to summon the Hovering Inferno"
    },
    "frame": "goal",
    "show_toast": true,
    "announce_to_chat": true,
    "hidden": false
  },
  "parent": "incendium:infernal_dunes/inferno/root",
  "criteria": {
    "requirement": {
      "trigger": "minecraft:impossible",
      "conditions": {}
    }
  }
}
